qkit/__init__.py
qkit/_version.py
qkit/analysis/CurveXtractor.py
qkit/analysis/IV_curve.py
qkit/analysis/IV_curve2.py
qkit/analysis/IV_curve3.py
qkit/analysis/Manual point picker.ipynb_template
qkit/analysis/__init__.py
qkit/analysis/avoided_crossing_fit.py
qkit/analysis/iq_cloud_analysis.ipynb_template
qkit/analysis/iq_cloud_analysis.py
qkit/analysis/manual_point_picker.py
qkit/analysis/pointtracker.py
qkit/analysis/qdata.py
qkit/analysis/qfit.py
qkit/analysis/qps_rings.py
qkit/analysis/resonator.py
qkit/analysis/sonnet_parser.py
qkit/analysis/spectroscopy.py
qkit/analysis/timedomain.py
qkit/analysis/uncertainties_utilities.py
qkit/analysis/circle_fit/__init__.py
qkit/analysis/circle_fit/circle_fit_2019/__init__.py
qkit/analysis/circle_fit/circle_fit_2019/circuit.py
qkit/analysis/circle_fit/circle_fit_classic/__init__.py
qkit/analysis/circle_fit/circle_fit_classic/calibration.py
qkit/analysis/circle_fit/circle_fit_classic/circlefit.py
qkit/analysis/circle_fit/circle_fit_classic/circuit.py
qkit/analysis/circle_fit/circle_fit_classic/utilities.py
qkit/config/.gitignore
qkit/config/README.md
qkit/config/__init__.py
qkit/config/config_holder.py
qkit/config/environment.py
qkit/config/local.py_template
qkit/config/services.py_template
qkit/core/.gitignore
qkit/core/README
qkit/core/VERSION
qkit/core/__init__.py
qkit/core/flow.py
qkit/core/instrument_base.py
qkit/core/instrument_basev2.py
qkit/core/instrument_tools.py
qkit/core/startup.py
qkit/core/lib/__init__.py
qkit/core/lib/list_dict_DB.py
qkit/core/lib/misc.py
qkit/core/lib/temp.py
qkit/core/lib/com/__init__.py
qkit/core/lib/com/info_client.py
qkit/core/lib/com/info_service.py
qkit/core/lib/com/ri_client.py
qkit/core/lib/com/ri_service.py
qkit/core/lib/com/signals.py
qkit/core/lib/file_service/__init__.py
qkit/core/lib/file_service/breadcrumbs.py
qkit/core/lib/file_service/file_info_database.py
qkit/core/lib/file_service/file_info_database_lib.py
qkit/core/lib/network/__init__.py
qkit/core/lib/network/tcpclient.py
qkit_core-0.4.6.dist-info/METADATA
qkit_core-0.4.6.dist-info/WHEEL
qkit_core-0.4.6.dist-info/entry_points.txt
qkit_core-0.4.6.dist-info/licenses/LICENSE
qkit_core-0.4.6.dist-info/RECORD
