Metadata-Version: 2.3
Name: qkit-core
Version: 0.4.6
Summary: qKIT quantum measurement suite in python
Project-URL: Homepage, https://github.com/qkitgroup/qkit
Project-URL: Bug Tracker, https://github.com/qkitgroup/qkit/issues
Author: PHI AG Ustinov
License-File: LICENSE
Keywords: Data Acquisition,Framework,Measurement,Quantum
Classifier: Framework :: Jupyter :: JupyterLab :: 3
Classifier: Intended Audience :: Science/Research
Classifier: License :: OSI Approved :: GNU General Public License v2 (GPLv2)
Requires-Python: >=3.7
Requires-Dist: h5py>=3.8
Requires-Dist: numpy>=1.24
Requires-Dist: pyqt5~=5.15
Requires-Dist: pyqtgraph~=0.13
Requires-Dist: pyvisa-py>=0.6
Requires-Dist: pyvisa>=1.13
Requires-Dist: pyzmq>=25
Requires-Dist: scipy>=1.10
Requires-Dist: tomli>=2.0.1
Provides-Extra: analysis
Requires-Dist: matplotlib>=3.7; extra == 'analysis'
Requires-Dist: peakutils>=1.3; extra == 'analysis'
Requires-Dist: qutip>=4.7; extra == 'analysis'
Requires-Dist: sqcircuit>=0.0.17; extra == 'analysis'
Requires-Dist: uncertainties>=3.1; extra == 'analysis'
Provides-Extra: jupyter
Requires-Dist: ipywidgets>=8.0; extra == 'jupyter'
Requires-Dist: jupyterlab-templates>=0.4; extra == 'jupyter'
Requires-Dist: jupyterlab>=3.6; extra == 'jupyter'
Provides-Extra: qgrid
Requires-Dist: qgrid>=1.0; extra == 'qgrid'
Provides-Extra: timedomain
Requires-Dist: zerorpc>=0.6; extra == 'timedomain'
Provides-Extra: zurich-instruments
Requires-Dist: zhinst~=23.2; extra == 'zurich-instruments'
